LICENSE
MANIFEST.in
README.md
setup.py
packtree/__init__.py
packtree/tree.py
packtree.egg-info/PKG-INFO
packtree.egg-info/SOURCES.txt
packtree.egg-info/dependency_links.txt
packtree.egg-info/top_level.txt