Metadata-Version: 1.0
Name: packtree
Version: 1.0.0
Summary: packtree makes ASCII tree representation of Python packages.
Home-page: https://github.com/pcubillos/packtree
Author: Patricio Cubillos
Author-email: patricio.cubillos@oeaw.ac.at
License: ['MIT']
Platform: UNKNOWN
